caspius/__init__.py
caspius/colors.py
caspius/logger.py
caspius-1.2.dist-info/LICENSE
caspius-1.2.dist-info/WHEEL
caspius-1.2.dist-info/METADATA
caspius-1.2.dist-info/RECORD
